subcvmfs/__init__.py
subcvmfs/__main__.py
subcvmfs/checkers.py
subcvmfs/config.py
subcvmfs/steps.py
subcvmfs_builder-1.0.1.dist-info/LICENSE
subcvmfs_builder-1.0.1.dist-info/METADATA
subcvmfs_builder-1.0.1.dist-info/WHEEL
subcvmfs_builder-1.0.1.dist-info/entry_points.txt
subcvmfs_builder-1.0.1.dist-info/top_level.txt
subcvmfs_builder-1.0.1.dist-info/RECORD
