Metadata-Version: 2.1
Name: subcvmfs-builder
Version: 1.0.1
Summary: Help to generate subsets of CVMFS
Home-page: https://gitlab.cern.ch/alboyer/subcvmfs-builder
Author: Alexandre F. Boyer
License: GPL-3.0-only
Classifier: Programming Language :: Python :: 3
Classifier: Programming Language :: Python :: 3.5
Classifier: Programming Language :: Python :: 3.6
Classifier: Programming Language :: Python :: 3.7
Classifier: Programming Language :: Python :: 3.8
Classifier: Programming Language :: Python :: 3.9
Classifier: License :: OSI Approved :: GNU General Public License v3 (GPLv3)
Classifier: Operating System :: OS Independent
Requires-Python: !=3.0.*,!=3.1.*,!=3.2.*,!=3.3.*,!=3.4.*
License-File: LICENSE
Provides-Extra: testing
Requires-Dist: pytest (>=4.6) ; extra == 'testing'
Requires-Dist: pytest-cov ; extra == 'testing'
Requires-Dist: pylint (>=1.6.5) ; extra == 'testing'
Requires-Dist: pycodestyle ; extra == 'testing'
